addthis/__init__.py
addthis/settings.py
addthis/templates/addthis/widget_js.html
addthis/templatetags/__init__.py
addthis/templatetags/addthis.py
addthis/tests/__init__.py
addthis/tests/conftest.py
addthis/tests/models.py
addthis/tests/settings.py
addthis/tests/test_templatetags.py
django_addthis-3.0.2.dist-info/AUTHORS
django_addthis-3.0.2.dist-info/LICENSE
django_addthis-3.0.2.dist-info/METADATA
django_addthis-3.0.2.dist-info/WHEEL
django_addthis-3.0.2.dist-info/top_level.txt
django_addthis-3.0.2.dist-info/RECORD
