Metadata-Version: 2.1
Name: django-addthis
Version: 3.0.2
Summary: Simple integration of the AddThis social sharing widget for Django projects.
Home-page: https://github.com/bashu/django-addthis
Author: Raymond Wanyoike
Maintainer: Basil Shubin
Maintainer-email: basil.shubin@gmail.com
License: GPLv3
Download-URL: https://github.com/bashu/django-addthis/zipball/master
Platform: UNKNOWN
Classifier: Development Status :: 5 - Production/Stable
Classifier: Environment :: Web Environment
Classifier: Intended Audience :: Developers
Classifier: License :: OSI Approved :: GNU General Public License v3 (GPLv3)
Classifier: Operating System :: OS Independent
Classifier: Programming Language :: Python
Classifier: Programming Language :: Python :: 3 :: Only
Classifier: Programming Language :: Python :: 3.6
Classifier: Programming Language :: Python :: 3.7
Classifier: Programming Language :: Python :: 3.8
Classifier: Programming Language :: Python :: 3.9
Classifier: Framework :: Django
Classifier: Framework :: Django :: 2.2
Classifier: Framework :: Django :: 3.0
Classifier: Framework :: Django :: 3.1
Classifier: Framework :: Django :: 3.2
License-File: LICENSE
License-File: AUTHORS
Provides-Extra: develop
Requires-Dist: tox ; extra == 'develop'
Requires-Dist: django ; extra == 'develop'
Requires-Dist: pytest-django ; extra == 'develop'
Requires-Dist: pytest ; extra == 'develop'
Provides-Extra: test
Requires-Dist: pytest-django ; extra == 'test'
Requires-Dist: pytest-cov ; extra == 'test'
Requires-Dist: pytest ; extra == 'test'
